odoo/addons/stock_move_line_reference_link/README.rst
odoo/addons/stock_move_line_reference_link/__init__.py
odoo/addons/stock_move_line_reference_link/__manifest__.py
odoo/addons/stock_move_line_reference_link/i18n/stock_move_line_reference_link.pot
odoo/addons/stock_move_line_reference_link/models/__init__.py
odoo/addons/stock_move_line_reference_link/models/stock_move_line.py
odoo/addons/stock_move_line_reference_link/readme/CONTRIBUTORS.rst
odoo/addons/stock_move_line_reference_link/readme/DESCRIPTION.rst
odoo/addons/stock_move_line_reference_link/static/description/icon.png
odoo/addons/stock_move_line_reference_link/static/description/index.html
odoo/addons/stock_move_line_reference_link/views/move_line_views.xml
odoo13_addon_stock_move_line_reference_link-13.0.1.0.1.dev4.dist-info/METADATA
odoo13_addon_stock_move_line_reference_link-13.0.1.0.1.dev4.dist-info/WHEEL
odoo13_addon_stock_move_line_reference_link-13.0.1.0.1.dev4.dist-info/top_level.txt
odoo13_addon_stock_move_line_reference_link-13.0.1.0.1.dev4.dist-info/RECORD
